letrista/__init__.py
letrista/bridge.py
letrista/chorus.py
letrista/cli.py
letrista/draft.py
letrista/editable_line.py
letrista/instruction.py
letrista/intro.py
letrista/letrista.py
letrista/line.py
letrista/outro.py
letrista/postchorus.py
letrista/prechorus.py
letrista/section.py
letrista/title.py
letrista/unassigned_section.py
letrista/verse.py
letrista-0.1.0.dist-info/LICENSE
letrista-0.1.0.dist-info/WHEEL
letrista-0.1.0.dist-info/METADATA
letrista-0.1.0.dist-info/RECORD
