Metadata-Version: 2.1
Name: letrista
Version: 0.1.0
Summary: Python3 package for lyrics writing and formating.
License: MIT
Author: Carlos Ramos
Author-email: carlos@ramoscarlos.com
Requires-Python: >=3.7
Classifier: License :: OSI Approved :: MIT License
Classifier: Programming Language :: Python :: 3
Classifier: Programming Language :: Python :: 3.7
Classifier: Programming Language :: Python :: 3.8
Classifier: Programming Language :: Python :: 3.9
Classifier: Programming Language :: Python :: 3.10
Classifier: Programming Language :: Python :: 3.11
